honeywell_imtcc_poller/__init__.py
honeywell_imtcc_poller/gateways/__init__.py
honeywell_imtcc_poller/gateways/honeywell.py
honeywell_imtcc_poller/gateways/openweather.py
honeywell_imtcc_poller/gateways/prometheus.py
honeywell_imtcc_poller/models/__init__.py
honeywell_imtcc_poller/models/zone_data.py
honeywell_imtcc_poller-0.5.0.dist-info/entry_points.txt
honeywell_imtcc_poller-0.5.0.dist-info/LICENSE.md
honeywell_imtcc_poller-0.5.0.dist-info/WHEEL
honeywell_imtcc_poller-0.5.0.dist-info/METADATA
honeywell_imtcc_poller-0.5.0.dist-info/RECORD
