Metadata-Version: 2.1
Name: honeywell-imtcc-poller
Version: 0.5.0
Summary: Tool for logging stats from the Honeywell international.mytotalconnectcomfort.com site
License: MIT
Author: Dave Randall
Author-email: 19395688+daveygit2050@users.noreply.github.com
Requires-Python: >=3.10,<4.0
Classifier: License :: OSI Approved :: MIT License
Classifier: Programming Language :: Python :: 3
Classifier: Programming Language :: Python :: 3.10
Requires-Dist: click (>=8.1.3,<9.0.0)
Requires-Dist: prometheus-client (>=0.14.1,<0.15.0)
Requires-Dist: requests (>=2.28.1,<3.0.0)
Requires-Dist: tenacity (>=8.0.1,<9.0.0)
